viewdoo/__init__.py
viewdoo/app.py
viewdoo/conversion copy.py
viewdoo/conversion.py
viewdoo/find_most_unaligned.py
viewdoo/header_controls.py
viewdoo/header_map.py
viewdoo/header_tag_conversions.py
viewdoo/prepare_dicom_slice.py
viewdoo/user_themes/Blue.json
viewdoo-0.1.4.dist-info/LICENSE.txt
viewdoo-0.1.4.dist-info/METADATA
viewdoo-0.1.4.dist-info/WHEEL
viewdoo-0.1.4.dist-info/top_level.txt
viewdoo-0.1.4.dist-info/RECORD
