Metadata-Version: 2.1
Name: viewdoo
Version: 0.1.4
Summary: Medical Image Viewing and Conversion Tool
Home-page: https://github.com/humunumuh/viewdoo
Author: Zachery Morton Colbert
Author-email: zachery.colbert@health.qld.gov.au
Classifier: Programming Language :: Python :: 3
Classifier: License :: OSI Approved :: GNU General Public License v3 (GPLv3)
Classifier: Operating System :: OS Independent
Requires-Python: >=3.6
License-File: LICENSE.txt
Requires-Dist: matplotlib
Requires-Dist: numpy
Requires-Dist: pydicom
Requires-Dist: opencv-python
Requires-Dist: rt-utils
Requires-Dist: scipy
Requires-Dist: customtkinter
Requires-Dist: nibabel
Requires-Dist: pynrrd
Requires-Dist: Pillow
Requires-Dist: SimpleITK
